{
  "name": "practice",
  "version": "0.1.0",
  "lockfileVersion": 3,
  "requires": true,
  "packages": {
    "": {
      "name": "practice",
      "version": "0.1.0",
      "dependencies": {
        "@testing-library/jest-dom": "^5.17.0",
        "@testing-library/react": "^13.4.0",
        "@testing-library/user-event": "^13.5.0",
        "axios": "^1.6.8",
        "cors": "^2.8.5",
        "express": "^4.18.3",
        "nodemon": "^3.1.0",
        "react": "^18.2.0",
        "react-dom": "^18.2.0",
        "react-router-dom": "^6.22.3",
        "react-scripts": "5.0.1",
        "web-vitals": "^2.1.4"
      }
    },
    "node_modules/@aashutoshrathi/word-wrap": {
      "version": "1.2.6",
      "resolved": "https://registry.npmjs.org/@aashutoshrathi/word-wrap/-/word-wrap-1.2.6.tgz",
      "integrity": "sha512-1Yjs2SvM8TflER/OD3cOjhWWOZb58A2t7wpE2S9XfBYTiIl+XFhQG2bjy4Pu1I+EAlCNUzRDYDdFwFYUKvXcIA==",
      "engines": {
        "node": ">=0.10.0"
      }
    },
    "node_modules/@adobe/css-tools": {
      "version": "4.3.3",
      "resolved": "https://registry.npmjs.org/@adobe/css-tools/-/css-tools-4.3.3.tgz",
      "integrity": "sha512-rE0Pygv0sEZ4vBWHlAgJLGDU7Pm8xoO6p3wsEceb7GYAjScrOHpEo8KK/eVkAcnSM+slAEtXjA2JpdjLp4fJQQ=="
    },
    "node_modules/@alloc/quick-lru": {
      "version": "5.2.0",
      "resolved": "https://registry.npmjs.org/@alloc/quick-lru/-/quick-lru-5.2.0.tgz",
      "integrity": "sha512-UrcABB+4bUrFABwbluTIBErXwvbsU/V7TZWfmbgJfbkwiBuziS9gxdODUyuiecfdGQ85jglMW6juS3+z5TsKLw==",
      "engines": {
        "node": ">=10"
      },
      "funding": {
        "url": "https://github.com/sponsors/sindresorhus"
      }
    },
    "node_modules/@ampproject/remapping": {
      "version": "2.3.0",
      "resolved": "https://registry.npmjs.org/@ampproject/remapping/-/remapping-2.3.0.tgz",
      "integrity": "sha512-30iZtAPgz+LTIYoeivqYo853f02jBYSd5uGnGpkFV0M3xOt9aN73erkgYAmZU43x4VfqcnLxW9Kpg3R5LC4YYw==",
      "dependencies": {
        "@jridgewell/gen-mapping": "^0.3.5",
        "@jridgewell/trace-mapping": "^0.3.24"
      },
      "engines": {
        "node": ">=6.0.0"
      }
    },
    "node_modules/@babel/code-frame": {
      "version": "7.24.2",
      "resolved": "https://registry.npmjs.org/@babel/code-frame/-/code-frame-7.24.2.tgz",
      "integrity": "sha512-y5+tLQyV8pg3fsiln67BVLD1P13Eg4lh5RW9mF0zUuvLrv9uIQ4MCL+CRT+FTsBlBjcIan6PGsLcBN0m3ClUyQ==",
      "dependencies": {
        "@babel/highlight": "^7.24.2",
        "picocolors": "^1.0.0"
      },
      "engines": {
        "node": ">=6.9.0"
      }
    },
    "node_modules/@babel/compat-data": {
      "version": "7.24.1",
      "resolved": "https://registry.npmjs.org/@babel/compat-data/-/compat-data-7.24.1.tgz",
      "integrity": "sha512-Pc65opHDliVpRHuKfzI+gSA4zcgr65O4cl64fFJIWEEh8JoHIHh0Oez1Eo8Arz8zq/JhgKodQaxEwUPRtZylVA==",
      "engines": {
        "node": ">=6.9.0"
      }
    },
    "node_modules/@babel/core": {
      "version": "7.24.1",
      "resolved": "https://registry.npmjs.org/@babel/core/-/core-7.24.1.tgz",
      "integrity": "sha512-F82udohVyIgGAY2VVj/g34TpFUG606rumIHjTfVbssPg2zTR7PuuEpZcX8JA6sgBfIYmJrFtWgPvHQuJamVqZQ==",
      "dependencies": {
        "@ampproject/remapping": "^2.2.0",
        "@babel/code-frame": "^7.24.1",
        "@babel/generator": "^7.24.1",
        "@babel/helper-compilation-targets": "^7.23.6",
        "@babel/helper-module-transforms": "^7.23.3",
        "@babel/helpers": "^7.24.1",
        "@babel/parser": "^7.24.1",
        "@babel/template": "^7.24.0",
        "@babel/traverse": "^7.24.1",
        "@babel/types": "^7.24.0",
        "convert-source-map": "^2.0.0",
        "debug": "^4.1.0",
        "gensync": "^1.0.0-beta.2",
        "json5": "^2.2.3",
        "semver": "^6.3.1"
      },
      "engines": {
        "node": ">=6.9.0"
      },
      "funding": {
        "type": "opencollective",
        "url": "https://opencollective.com/babel"
      }
    },
    "node_modules/@babel/core/node_modules/semver": {
      "version": "6.3.1",
      "resolved": "https://registry.npmjs.org/semver/-/semver-6.3.1.tgz",
      "integrity": "sha512-BR7VvDCVHO+q2xBEWskxS6DJE1qRnb7DxzUrogb71CWoSficBxYsiAGd+Kl0mmq/MprG9yArRkyrQxTO6XjMzA==",
      "bin": {
        "semver": "bin/semver.js"
      }
    },
    "node_modules/@babel/eslint-parser": {
      "version": "7.24.1",
      "resolved": "https://registry.npmjs.org/@babel/eslint-parser/-/eslint-parser-7.24.1.tgz",
      "integrity": "sha512-d5guuzMlPeDfZIbpQ8+g1NaCNuAGBBGNECh0HVqz1sjOeVLh2CEaifuOysCH18URW6R7pqXINvf5PaR/dC6jLQ==",
      "dependencies": {
        "@nicolo-ribaudo/eslint-scope-5-internals": "5.1.1-v1",
        "eslint-visitor-keys": "^2.1.0",
        "semver": "^6.3.1"
      },
      "engines": {
        "node": "^10.13.0 || ^12.13.0 || >=14.0.0"
      },
      "peerDependencies": {
        "@babel/core": "^7.11.0",
        "eslint": "^7.5.0 || ^8.0.0"
      }
    },
    "node_modules/@babel/eslint-parser/node_modules/eslint-visitor-keys": {
      "version": "2.1.0",
      "resolved": "https://registry.npmjs.org/eslint-visitor-keys/-/eslint-visitor-keys-2.1.0.tgz",
      "integrity": "sha512-0rSmRBzXgDzIsD6mGdJgevzgezI534Cer5L/vyMX0kHzT/jiB43jRhd9YUlMGYLQy2zprNmoT8qasCGtY+QaKw==",
      "engines": {
        "node": ">=10"
      }
    },
    "node_modules/@babel/eslint-parser/node_modules/semver": {
      "version": "6.3.1",
      "resolved": "https://registry.npmjs.org/semver/-/semver-6.3.1.tgz",
      "integrity": "sha512-BR7VvDCVHO+q2xBEWskxS6DJE1qRnb7DxzUrogb71CWoSficBxYsiAGd+Kl0mmq/MprG9yArRkyrQxTO6XjMzA==",
      "bin": {
        "semver": "bin/semver.js"
      }
    },
    "node_modules/@babel/generator": {
      "version": "7.24.1",
      "resolved": "https://registry.npmjs.org/@babel/generator/-/generator-7.24.1.tgz",
      "integrity": "sha512-DfCRfZsBcrPEHUfuBMgbJ1Ut01Y/itOs+hY2nFLgqsqXd52/iSiVq5TITtUasIUgm+IIKdY2/1I7auiQOEeC9A==",
      "dependencies": {
        "@babel/types": "^7.24.0",
        "@jridgewell/gen-mapping": "^0.3.5",
        "@jridgewell/trace-mapping": "^0.3.25",
        "jsesc": "^2.5.1"
      },
      "engines": {
        "node": ">=6.9.0"
      }
    },
    "node_modules/@babel/helper-annotate-as-pure": {
      "version": "7.22.5",
      "resolved": "https://registry.npmjs.org/@babel/helper-annotate-as-pure/-/helper-annotate-as-pure-7.22.5.tgz",
      "integrity": "sha512-LvBTxu8bQSQkcyKOU+a1btnNFQ1dMAd0R6PyW3arXes06F6QLWLIrd681bxRPIXlrMGR3XYnW9JyML7dP3qgxg==",
      "dependencies": {
        "@babel/types": "^7.22.5"
      },
      "engines": {
        "node": ">=6.9.0"
      }
    },
    "node_modules/@babel/helper-builder-binary-assignment-operator-visitor": {
      "version": "7.22.15",
      "resolved": "https://registry.npmjs.org/@babel/helper-builder-binary-assignment-operator-visitor/-/helper-builder-binary-assignment-operator-visitor-7.22.15.tgz",
      "integrity": "sha512-QkBXwGgaoC2GtGZRoma6kv7Szfv06khvhFav67ZExau2RaXzy8MpHSMO2PNoP2XtmQphJQRHFfg77Bq731Yizw==",
      "dependencies": {
        "@babel/types": "^7.22.15"
      },
      "engines": {
        "node": ">=6.9.0"
      }
    },
    "node_modules/@babel/helper-compilation-targets": {
      "version": "7.23.6",
      "resolved": "https://registry.npmjs.org/@babel/helper-compilation-targets/-/helper-compilation-targets-7.23.6.tgz",
      "integrity": "sha512-9JB548GZoQVmzrFgp8o7KxdgkTGm6xs9DW0o/Pim72UDjzr5ObUQ6ZzYPqA+g9OTS2bBQoctLJrky0RDCAWRgQ==",
      "dependencies": {
        "@babel/compat-data": "^7.23.5",
        "@babel/helper-validator-option": "^7.23.5",
        "browserslist": "^4.22.2",
        "lru-cache": "^5.1.1",
        "semver": "^6.3.1"
      },
      "engines": {
        "node": ">=6.9.0"
      }
    },
    "node_modules/@babel/helper-compilation-targets/node_modules/semver": {
      "version": "6.3.1",
      "resolved": "https://registry.npmjs.org/semver/-/semver-6.3.1.tgz",
      "integrity": "sha512-BR7VvDCVHO+q2xBEWskxS6DJE1qRnb7DxzUrogb71CWoSficBxYsiAGd+Kl0mmq/MprG9yArRkyrQxTO6XjMzA==",
      "bin": {
        "semver": "bin/semver.js"
      }
    },
    "node_modules/@babel/helper-create-class-features-plugin": {
      "version": "7.24.1",
      "resolved": "https://registry.npmjs.org/@babel/helper-create-class-features-plugin/-/helper-create-class-features-plugin-7.24.1.tgz",
      "integrity": "sha512-1yJa9dX9g//V6fDebXoEfEsxkZHk3Hcbm+zLhyu6qVgYFLvmTALTeV+jNU9e5RnYtioBrGEOdoI2joMSNQ/+aA==",
      "dependencies": {
        "@babel/helper-annotate-as-pure": "^7.22.5",
        "@babel/helper-environment-visitor": "^7.22.20",
        "@babel/helper-function-name": "^7.23.0",
        "@babel/helper-member-expression-to-functions": "^7.23.0",
        "@babel/helper-optimise-call-expression": "^7.22.5",
        "@babel/helper-replace-supers": "^7.24.1",
        "@babel/helper-skip-transparent-expression-wrappers": "^7.22.5",
        "@babel/helper-split-export-declaration": "^7.22.6",
        "semver": "^6.3.1"
      },
      "engines": {
        "node": ">=6.9.0"
      },
      "peerDependencies": {
        "@babel/core": "^7.0.0"
      }
    },
    "node_modules/@babel/helper-create-class-features-plugin/node_modules/semver": {
      "version": "6.3.1",
      "resolved": "https://registry.npmjs.org/semver/-/semver-6.3.1.tgz",
      "integrity": "sha512-BR7VvDCVHO+q2xBEWskxS6DJE1qRnb7DxzUrogb71CWoSficBxYsiAGd+Kl0mmq/MprG9yArRkyrQxTO6XjMzA==",
      "bin": {
        "semver": "bin/semver.js"
      }
    },
    "node_modules/@babel/helper-create-regexp-features-plugin": {
      "version": "7.22.15",
      "resolved": "https://registry.npmjs.org/@babel/helper-create-regexp-features-plugin/-/helper-create-regexp-features-plugin-7.22.15.tgz",
      "integrity": "sha512-29FkPLFjn4TPEa3RE7GpW+qbE8tlsu3jntNYNfcGsc49LphF1PQIiD+vMZ1z1xVOKt+93khA9tc2JBs3kBjA7w==",
      "dependencies": {
        "@babel/helper-annotate-as-pure": "^7.22.5",
        "regexpu-core": "^5.3.1",
        "semver": "^6.3.1"
      },
      "engines": {
        "node": ">=6.9.0"
      },
      "peerDependencies": {
        "@babel/core": "^7.0.0"
      }
    },
    "node_modules/@babel/helper-create-regexp-features-plugin/node_modules/semver": {
      "version": "6.3.1",
      "resolved": "https://registry.npmjs.org/semver/-/semver-6.3.1.tgz",
      "integrity": "sha512-BR7VvDCVHO+q2xBEWskxS6DJE1qRnb7DxzUrogb71CWoSficBxYsiAGd+Kl0mmq/MprG9yArRkyrQxTO6XjMzA==",
      "bin": {
        "semver": "bin/semver.js"
      }
    },
    "node_modules/@babel/helper-define-polyfill-provider": {
      "version": "0.6.1",
      "resolved": "https://registry.npmjs.org/@babel/helper-define-polyfill-provider/-/helper-define-polyfill-provider-0.6.1.tgz",
      "integrity": "sha512-o7SDgTJuvx5vLKD6SFvkydkSMBvahDKGiNJzG22IZYXhiqoe9efY7zocICBgzHV4IRg5wdgl2nEL/tulKIEIbA==",
      "dependencies": {
        "@babel/helper-compilation-targets": "^7.22.6",
        "@babel/helper-plugin-utils": "^7.22.5",
        "debug": "^4.1.1",
        "lodash.debounce": "^4.0.8",
        "resolve": "^1.14.2"
      },
      "peerDependencies": {
        "@babel/core": "^7.4.0 || ^8.0.0-0 <8.0.0"
      }
    },
    "node_modules/@babel/helper-environment-visitor": {
      "version": "7.22.20",
      "resolved": "https://registry.npmjs.org/@babel/helper-environment-visitor/-/helper-environment-visitor-7.22.20.tgz",
      "integrity": "sha512-zfedSIzFhat/gFhWfHtgWvlec0nqB9YEIVrpuwjruLlXfUSnA8cJB0miHKwqDnQ7d32aKo2xt88/xZptwxbfhA==",
      "engines": {
        "node": ">=6.9.0"
      }
    },
    "node_modules/@babel/helper-function-name": {
      "version": "7.23.0",
      "resolved": "https://registry.npmjs.org/@babel/helper-function-name/-/helper-function-name-7.23.0.tgz",
      "integrity": "sha512-OErEqsrxjZTJciZ4Oo+eoZqeW9UIiOcuYKRJA4ZAgV9myA+pOXhhmpfNCKjEH/auVfEYVFJ6y1Tc4r0eIApqiw==",
      "dependencies": {
        "@babel/template": "^7.22.15",
        "@babel/types": "^7.23.0"
      },
      "engines": {
        "node": ">=6.9.0"
      }
    },
    "node_modules/@babel/helper-hoist-variables": {
      "version": "7.22.5",
      "resolved": "https://registry.npmjs.org/@babel/helper-hoist-variables/-/helper-hoist-variables-7.22.5.tgz",
      "integrity": "sha512-wGjk9QZVzvknA6yKIUURb8zY3grXCcOZt+/7Wcy8O2uctxhplmUPkOdlgoNhmdVee2c92JXbf1xpMtVNbfoxRw==",
      "dependencies": {
        "@babel/types": "^7.22.5"
      },
      "engines": {
        "node": ">=6.9.0"
      }
    },
    "node_modules/@babel/helper-member-expression-to-functions": {
      "version": "7.23.0",
      "resolved": "https://registry.npmjs.org/@babel/helper-member-expression-to-functions/-/helper-member-expression-to-functions-7.23.0.tgz",
      "integrity": "sha512-6gfrPwh7OuT6gZyJZvd6WbTfrqAo7vm4xCzAXOusKqq/vWdKXphTpj5klHKNmRUU6/QRGlBsyU9mAIPaWHlqJA==",
      "dependencies": {
        "@babel/types": "^7.23.0"
      },
      "engines": {
        "node": ">=6.9.0"
      }
    },
    "node_modules/@babel/helper-module-imports": {
      "version": "7.24.1",
      "resolved": "https://registry.npmjs.org/@babel/helper-module-imports/-/helper-module-imports-7.24.1.tgz",
      "integrity": "sha512-HfEWzysMyOa7xI5uQHc/OcZf67/jc+xe/RZlznWQHhbb8Pg1SkRdbK4yEi61aY8wxQA7PkSfoojtLQP/Kpe3og==",
      "dependencies": {
        "@babel/types": "^7.24.0"
      },
      "engines": {
        "node": ">=6.9.0"
      }
    },
    "node_modules/@babel/helper-module-transforms": {
      "version": "7.23.3",
      "resolved": "https://registry.npmjs.org/@babel/helper-module-transforms/-/helper-module-transforms-7.23.3.tgz",
      "integrity": "sha512-7bBs4ED9OmswdfDzpz4MpWgSrV7FXlc3zIagvLFjS5H+Mk7Snr21vQ6QwrsoCGMfNC4e4LQPdoULEt4ykz0SRQ==",
      "dependencies": {
        "@babel/helper-environment-visitor": "^7.22.20",
        "@babel/helper-module-imports": "^7.22.15",
        "@babel/helper-simple-access": "^7.22.5",
        "@babel/helper-split-export-declaration": "^7.22.6",
        "@babel/helper-validator-identifier": "^7.22.20"
      },
      "engines": {
        "node": ">=6.9.0"
      },
      "peerDependencies": {
        "@babel/core": "^7.0.0"
      }
    },
    "node_modules/@babel/helper-optimise-call-expression": {
      "version": "7.22.5",
      "resolved": "https://registry.npmjs.org/@babel/helper-optimise-call-expression/-/helper-optimise-call-expression-7.22.5.tgz",
      "integrity": "sha512-HBwaojN0xFRx4yIvpwGqxiV2tUfl7401jlok564NgB9EHS1y6QT17FmKWm4ztqjeVdXLuC4fSvHc5ePpQjoTbw==",
      "dependencies": {
        "@babel/types": "^7.22.5"
      },
      "engines": {
        "node": ">=6.9.0"
      }
    },
    "node_modules/@babel/helper-plugin-utils": {
      "version": "7.24.0",
      "resolved": "https://registry.npmjs.org/@babel/helper-plugin-utils/-/helper-plugin-utils-7.24.0.tgz",
      "integrity": "sha512-9cUznXMG0+FxRuJfvL82QlTqIzhVW9sL0KjMPHhAOOvpQGL8QtdxnBKILjBqxlHyliz0yCa1G903ZXI/FuHy2w==",
      "engines": {
        "node": ">=6.9.0"
      }
    },
    "node_modules/@babel/helper-remap-async-to-generator": {
      "version": "7.22.20",
      "resolved": "https://registry.npmjs.org/@babel/helper-remap-async-to-generator/-/helper-remap-async-to-generator-7.22.20.tgz",
      "integrity": "sha512-pBGyV4uBqOns+0UvhsTO8qgl8hO89PmiDYv+/COyp1aeMcmfrfruz+/nCMFiYyFF/Knn0yfrC85ZzNFjembFTw==",
      "dependencies": {
        "@babel/helper-annotate-as-pure": "^7.22.5",
        "@babel/helper-environment-visitor": "^7.22.20",
        "@babel/helper-wrap-function": "^7.22.20"
      },
      "engines": {
        "node": ">=6.9.0"
      },
      "peerDependencies": {
        "@babel/core": "^7.0.0"
      }
    },
    "node_modules/@babel/helper-replace-supers": {
      "version": "7.24.1",
      "resolved": "https://registry.npmjs.org/@babel/helper-replace-supers/-/helper-replace-supers-7.24.1.tgz",
      "integrity": "sha512-QCR1UqC9BzG5vZl8BMicmZ28RuUBnHhAMddD8yHFHDRH9lLTZ9uUPehX8ctVPT8l0TKblJidqcgUUKGVrePleQ==",
      "dependencies": {
        "@babel/helper-environment-visitor": "^7.22.20",
        "@babel/helper-member-expression-to-functions": "^7.23.0",
        "@babel/helper-optimise-call-expression": "^7.22.5"
      },
      "engines": {
        "node": ">=6.9.0"
      },
      "peerDependencies": {
        "@babel/core": "^7.0.0"
      }
    },
    "node_modules/@babel/helper-simple-access": {
      "version": "7.22.5",
      "resolved": "https://registry.npmjs.org/@babel/helper-simple-access/-/helper-simple-access-7.22.5.tgz",
      "integrity": "sha512-n0H99E/K+Bika3++WNL17POvo4rKWZ7lZEp1Q+fStVbUi8nxPQEBOlTmCOxW/0JsS56SKKQ+ojAe2pHKJHN35w==",
      "dependencies": {
        "@babel/types": "^7.22.5"
      },
      "engines": {
        "node": ">=6.9.0"
      }
    },
    "node_modules/@babel/helper-skip-transparent-expression-wrappers": {
      "version": "7.22.5",
      "resolved": "https://registry.npmjs.org/@babel/helper-skip-transparent-expression-wrappers/-/helper-skip-transparent-expression-wrappers-7.22.5.tgz",
      "integrity": "sha512-tK14r66JZKiC43p8Ki33yLBVJKlQDFoA8GYN67lWCDCqoL6EMMSuM9b+Iff2jHaM/RRFYl7K+iiru7hbRqNx8Q==",
      "dependencies": {
        "@babel/types": "^7.22.5"
      },
      "engines": {
        "node": ">=6.9.0"
      }
    },
    "node_modules/@babel/helper-split-export-declaration": {
      "version": "7.22.6",
      "resolved": "https://registry.npmjs.org/@babel/helper-split-export-declaration/-/helper-split-export-declaration-7.22.6.tgz",
      "integrity": "sha512-AsUnxuLhRYsisFiaJwvp1QF+I3KjD5FOxut14q/GzovUe6orHLesW2C7d754kRm53h5gqrz6sFl6sxc4BVtE/g==",
      "dependencies": {
        "@babel/types": "^7.22.5"
      },
      "engines": {
        "node": ">=6.9.0"
      }
    },
    "node_modules/@babel/helper-string-parser": {
      "version": "7.24.1",
      "resolved": "https://registry.npmjs.org/@babel/helper-string-parser/-/helper-string-parser-7.24.1.tgz",
      "integrity": "sha512-2ofRCjnnA9y+wk8b9IAREroeUP02KHp431N2mhKniy2yKIDKpbrHv9eXwm8cBeWQYcJmzv5qKCu65P47eCF7CQ==",
      "engines": {
        "node": ">=6.9.0"
      }
    },
    "node_modules/@babel/helper-validator-identifier": {
      "version": "7.22.20",
      "resolved": "https://registry.npmjs.org/@babel/helper-validator-identifier/-/helper-validator-identifier-7.22.20.tgz",
      "integrity": "sha512-Y4OZ+ytlatR8AI+8KZfKuL5urKp7qey08ha31L8b3BwewJAoJamTzyvxPR/5D+KkdJCGPq/+8TukHBlY10FX9A==",
      "engines": {
        "node": ">=6.9.0"
      }
    },
    "node_modules/@babel/helper-validator-option": {
      "version": "7.23.5",
      "resolved": "https://registry.npmjs.org/@babel/helper-validator-option/-/helper-validator-option-7.23.5.tgz",
      "integrity": "sha512-85ttAOMLsr53VgXkTbkx8oA6YTfT4q7/HzXSLEYmjcSTJPMPQtvq1BD79Byep5xMUYbGRzEpDsjUf3dyp54IKw==",
      "engines": {
        "node": ">=6.9.0"
      }
    },
    "node_modules/@babel/helper-wrap-function": {
      "version": "7.22.20",
      "resolved": "https://registry.npmjs.org/@babel/helper-wrap-function/-/helper-wrap-function-7.22.20.tgz",
      "integrity": "sha512-pms/UwkOpnQe/PDAEdV/d7dVCoBbB+R4FvYoHGZz+4VPcg7RtYy2KP7S2lbuWM6FCSgob5wshfGESbC/hzNXZw==",
      "dependencies": {
        "@babel/helper-function-name": "^7.22.5",
        "@babel/template": "^7.22.15",
        "@babel/types": "^7.22.19"
      },
      "engines": {
        "node": ">=6.9.0"
      }
    },
    "node_modules/@babel/helpers": {
      "version": "7.24.1",
      "resolved": "https://registry.npmjs.org/@babel/helpers/-/helpers-7.24.1.tgz",
      "integrity": "sha512-BpU09QqEe6ZCHuIHFphEFgvNSrubve1FtyMton26ekZ85gRGi6LrTF7zArARp2YvyFxloeiRmtSCq5sjh1WqIg==",
      "dependencies": {
        "@babel/template": "^7.24.0",
        "@babel/traverse": "^7.24.1",
        "@babel/types": "^7.24.0"
      },
      "engines": {
        "node": ">=6.9.0"
      }
    },
    "node_modules/@babel/highlight": {
      "version": "7.24.2",
      "resolved": "https://registry.npmjs.org/@babel/highlight/-/highlight-7.24.2.tgz",
      "integrity": "sha512-Yac1ao4flkTxTteCDZLEvdxg2fZfz1v8M4QpaGypq/WPDqg3ijHYbDfs+LG5hvzSoqaS
